{
    "version": "1.0.1",
    "architecture": {
        "arm64": {
            "url": "https://github.com/louiss0/javascript-package-delegator/releases/download/v1.0.1/javascript-package-delegator_1.0.1_windows_arm64.zip",
            "bin": [
                "jpd.exe"
            ],
            "hash": "4badd527e04fe2c4e27f8caa13018803a1cf78a4b3e032804cfd7d7b54ff3a86"
        }
    },
    "homepage": "https://github.com/louiss0/javascript-package-delegator",
    "description": "A CLI for executing Javascript Package Manager Commands based on lock files. Supported's deno,bun, and all node package managers",
    "shortcuts": [
        [
            "javascript-package-delegator.exe",
            "jpd"
        ]
    ]
}